README.rst
setup.py
merlyn/__init__.py
merlyn/_version.py
merlyn/auth.py
merlyn/exercise.py
merlyn/manhole.py
merlyn/multiplexing.py
merlyn/service.py
merlyn.egg-info/PKG-INFO
merlyn.egg-info/SOURCES.txt
merlyn.egg-info/dependency_links.txt
merlyn.egg-info/requires.txt
merlyn.egg-info/top_level.txt
merlyn.egg-info/zip-safe
merlyn/test/__init__.py
merlyn/test/test_auth.py
merlyn/test/test_exercise.py
merlyn/test/test_multiplexing.py
merlyn/test/test_service.py
twisted/plugins/merlyn_plugin.py