Metadata-Version: 1.1
Name: merlyn
Version: 0.0.7
Summary: A server backend for interactive online exercises.
Home-page: https://github.com/crypto101/merlyn
Author: Laurens Van Houtven
Author-email: _@lvh.io
License: ISC
Keywords: crypto twisted
Platform: UNKNOWN
Classifier: Development Status :: 3 - Alpha
Classifier: Framework :: Twisted
Classifier: Intended Audience :: Education
Classifier: License :: OSI Approved :: ISC License (ISCL)
Classifier: Programming Language :: Python :: 2 :: Only
Classifier: Programming Language :: Python :: 2.6
Classifier: Programming Language :: Python :: 2.7
Classifier: Topic :: Education
Classifier: Topic :: Games/Entertainment
Classifier: Topic :: Security :: Cryptography
